{
    "fielding_in": [
        "England"
    ], 
    "other_officers": [], 
    "deregistered_date": "2008-07-04T00:00:00", 
    "campaigns_officer": "None", 
    "registered_date": "2005-07-28T00:00:00", 
    "postcode": "BR5 2NS", 
    "party_leader": "Mr Paul O'Callaghan", 
    "nominating_officer": "Christine Anne Weedon", 
    "emblems": [], 
    "party_address": "11 Wimborne Avenue\r\nOrpington\r\nKent\r\nBR5 2NS\r\nUnited Kingdom\r\n", 
    "email": "", 
    "gibraltar_party": false, 
    "financial_year_end": null, 
    "status": "Statutorily Deregistered", 
    "fax": "", 
    "end_date": "2009-12-31T00:00:00", 
    "phone_extension": "", 
    "phone": "", 
    "treasurer": "None", 
    "party_id": "PPm502", 
    "accounting_units": {
        "exempt_from_parliamentary_election_returns": false, 
        "exempt_from_quarterly_transaction_returns": false, 
        "exempt_from_quarterly_donation_returns": false
    }, 
    "geometry": {
        "coordinates ": [
            0.09520311628644068, 
            51.39608120262535
        ], 
        "type": "Point"
    }, 
    "register": "Great Britain", 
    "party_name": "British Unicorn Party", 
    "alternative_names": [
        ""
    ], 
    "descriptions": []
}