{
    "fielding_in": [], 
    "other_officers": [
        {
            "deputy_additional_officer": false, 
            "deputy_nominating_officer": false, 
            "name": "Mr Roger Lyons", 
            "deputy_campaigns_officer": false, 
            "deputy_treasurer": false
        }
    ], 
    "campaigns_officer": "None", 
    "registered_date": "2001-05-23T00:00:00", 
    "postcode": "EC1U 8HA", 
    "party_leader": "None", 
    "nominating_officer": "None", 
    "emblems": [], 
    "party_address": "33 - 37 Moreland Street\r\nno town\r\nLondon\r\nEC1U 8HA\r\nUnited Kingdom\r\n", 
    "email": "", 
    "gibraltar_party": false, 
    "financial_year_end": null, 
    "status": "Lapsed", 
    "fax": "", 
    "end_date": null, 
    "phone_extension": "", 
    "phone": "", 
    "treasurer": "None", 
    "party_id": "TP915", 
    "accounting_units": {
        "exempt_from_parliamentary_election_returns": null, 
        "exempt_from_quarterly_transaction_returns": false, 
        "exempt_from_quarterly_donation_returns": false
    }, 
    "geometry": {
        "type": "Point", 
        "coordinates": null
    }, 
    "register": null, 
    "party_name": "Manufacturing, Science & Finance Union", 
    "alternative_names": [
        ""
    ], 
    "descriptions": []
}